pycosmicwrap/__init__.py
pycosmicwrap/wrapper.py
pycosmicwrap-0.1.4.dist-info/METADATA
pycosmicwrap-0.1.4.dist-info/WHEEL
pycosmicwrap-0.1.4.dist-info/licenses/LICENSE
pycosmicwrap-0.1.4.dist-info/RECORD
