Metadata-Version: 2.1
Name: pyCosmicWrap
Version: 0.1.4
Summary: pyCosmicWrap is a Cosmos API/RPC python Wrapper by ChihuahuaChain
Project-URL: Homepage, https://github.com/ChihuahuaChain/pyCosmicWrap
Project-URL: Bug Tracker, https://github.com/ChihuahuaChain/pyCosmicWrap/issues
Author-email: ChihuahuaChain <woof@huahua.wtf>
License: GNU General Public License v3.0
License-File: LICENSE
Keywords: chihuahua,chihuahuachain,cosmos,cosmosecosystem,pycosmicwrap,wrapper
Requires-Python: >=3.7
Requires-Dist: requests~=2.25.1
